{
  "元數據": {
    "方案名": "冰雪清韻",
    "標識符": "snow-qingyun",
    "作者": "譚凇宸",
    "版本": "20251125",
    "官網": "https://input.tansongchen.com/snow-qingyun/",
    "碼表下載鏈接": "https://zhuyuhao.com/yuhao-assess-data/tables/snow-qingyun.txt",
    "描述": "四碼限長前綴碼",
    "標籤": [
      "形碼",
      "前綴碼",
      "四碼限長"
    ],
    "創建時間": "2026-02-04T00:00:00.000Z",
    "更新時間": "2026-02-06T22:49:48.165Z"
  },
  "方案參數": {
    "編碼終止指示符列表": [
      "a",
      "o",
      "e",
      "i",
      "u",
      ";",
      ",",
      ".",
      "/",
      "_"
    ],
    "最大碼長": 4,
    "編碼規則": {
      "單字編碼規則": "",
      "詞語編碼規則": ""
    }
  },
  "碼表元數據": {
    "分隔符": "製表符",
    "第一列類型": "字符",
    "哈希值": "963e9594c311b2d38e223c3505ed32ece9ef17174beeb6b25d490f65b2c4b7b6",
    "總字符數": 97668
  },
  "簡碼效率分析結果": {
    "知乎簡體字頻下之簡碼效率": {
      "完整字符字符串": "的不是我有这在了就你以来都时到说能会他多和好学对得后国家想要而为最所实也之自没可看很地做些着还中理过感那生给然第问动但去发经分比度其前再面因成进种作点吃高答知事题道样被情意起从行别两更关常法她打性相身直机把美部间校重先四外应质男喜数爱基考原完接加结等话提通算平该跟单表区活位买网世量系找始期专影品总物变选语民程资难带图听清书制路孩简保强玩流建格微读刚界钱左处战哪海拿历试北某英哈字片求色黑服政式深运持近照转指快五空员易望案据够房住标概存满准球军优除离城错远随功许务费却吧脑调值低希极众母院华班客模验乎领似效星换步楼爸拍配怕课际号群病态慢择遇切修压岁脸啊衣团愿懂睡层婚族害互店营待追黄息查啥笔武朝顺赛销律缺荐李谓增局构款测责阶略置既划铁姑怀刷暴龙操菜麻键右减警钟疑娘尤述邀亮颜贵脚索弹杂镜辈察均楚域河松婆派降策藏避惯媒临宗虚威露困拥封零骗胜彩符呼链貌幕舞雄龄忙鞋叔炸槽骑宜灯授阵途净钢肥震屁筑炒废幼惜宽嫌佳抄宫汤腰瞬疯辩琴吵郁乏彻喊脂娱耗颗铺爬屋峰瞎拔梅珍惨遭曼腹胎桥嫁盟宠愤崇娃坛圾荒席驱幽呀锋桃艳喂埋遥岸勉肃盐萝驶腻赫御朴蛇董嗯晕笼芝逢驻弦谐袁咸衷杠铃霜桂陵巫晴伞怼厢寓铅哔琳瑕塘咯琪疤婷栽禽怯瑶惫",
      "N值結果": [
        {
          "最有效率的簡碼個數": 0,
          "字頻加權碼長": 3.6008058042983224
        },
        {
          "最有效率的簡碼個數": 5,
          "字頻加權碼長": 3.312071986072795
        },
        {
          "最有效率的簡碼個數": 10,
          "字頻加權碼長": 3.22861342989085
        },
        {
          "最有效率的簡碼個數": 25,
          "字頻加權碼長": 3.087542354680176
        },
        {
          "最有效率的簡碼個數": 50,
          "字頻加權碼長": 2.961771849336172
        },
        {
          "最有效率的簡碼個數": 75,
          "字頻加權碼長": 2.894677047150608
        },
        {
          "最有效率的簡碼個數": 100,
          "字頻加權碼長": 2.8520727899528873
        },
        {
          "最有效率的簡碼個數": 150,
          "字頻加權碼長": 2.798971026474473
        },
        {
          "最有效率的簡碼個數": 200,
          "字頻加權碼長": 2.7668499275556986
        },
        {
          "最有效率的簡碼個數": 250,
          "字頻加權碼長": 2.74408789877873
        },
        {
          "最有效率的簡碼個數": 300,
          "字頻加權碼長": 2.728637689893806
        },
        {
          "最有效率的簡碼個數": 400,
          "字頻加權碼長": 2.7137064420721964
        },
        {
          "最有效率的簡碼個數": 500,
          "字頻加權碼長": 2.7097739855924345
        },
        {
          "最有效率的簡碼個數": 600,
          "字頻加權碼長": 2.7097739855924345
        },
        {
          "最有效率的簡碼個數": 700,
          "字頻加權碼長": 2.7097739855924345
        },
        {
          "最有效率的簡碼個數": 800,
          "字頻加權碼長": 2.7097739855924345
        },
        {
          "最有效率的簡碼個數": 900,
          "字頻加權碼長": 2.7097739855924345
        },
        {
          "最有效率的簡碼個數": 1000,
          "字頻加權碼長": 2.7097739855924345
        },
        {
          "最有效率的簡碼個數": 1100,
          "字頻加權碼長": 2.7097739855924345
        },
        {
          "最有效率的簡碼個數": 1200,
          "字頻加權碼長": 2.7097739855924345
        },
        {
          "最有效率的簡碼個數": 1300,
          "字頻加權碼長": 2.7097739855924345
        },
        {
          "最有效率的簡碼個數": 1400,
          "字頻加權碼長": 2.7097739855924345
        },
        {
          "最有效率的簡碼個數": 1500,
          "字頻加權碼長": 2.7097739855924345
        },
        {
          "最有效率的簡碼個數": 1600,
          "字頻加權碼長": 2.7097739855924345
        },
        {
          "最有效率的簡碼個數": 1700,
          "字頻加權碼長": 2.7097739855924345
        },
        {
          "最有效率的簡碼個數": 1800,
          "字頻加權碼長": 2.7097739855924345
        },
        {
          "最有效率的簡碼個數": 1900,
          "字頻加權碼長": 2.7097739855924345
        },
        {
          "最有效率的簡碼個數": 2000,
          "字頻加權碼長": 2.7097739855924345
        }
      ]
    },
    "北語簡體字頻下之簡碼效率": {
      "完整字符字符串": "的不我了是在有这他来你说到就着地时好得会后以都和对想能之道而那也多家看要她中没些然为过自去可所还动国给起进再实最学第感生身吧样事面做知很点前发经情理把话意但成两四从间被问吃打法行种分高听作其却啊因军外度住相等别色部战直重脸比快应难更美位关机接先处望常完清刚跟爱龙空带找原李平变强男该路海加远活解世性表许黑转总算城孩校始满物离似通五乎量结怕流指书微步左喜影深钱提随服武哪数房题衣拿星功系近界字民切忙员哈制息保片阵语错极慢领准华质答众够求害单脚脑楚北格朝族团母亮客照易黄修球呀院玩待楼呼期英低持政运睡希怀露娘式除考建愿程务品疑调爸派铁资群号病威追简基选历试存区右态买局班图岁顺既松费拍钟警宫压河查察胜遇据骑贵屋换层喊婚划置模舞姑麻责营案专店弹标际某封藏震虚梅临宗索婆值读叔网雄赛略拥灯菜验暴辈懂效优杂彩笔惜避配择课峰疯腰镜幽降颜谓操锋瞬尤概增困律惨惯互策席缺愤阶测遥幕净珍爬炸颗嗯佳骗拔宽遭彻御貌述琴蛇晕屁零盟途郁琳构销废曼宜喂艳晴董埋款荒域授桥减岸肃铺汤婷赫符吵鞋均龄钢嫁键袁筑崇娃桃铃腹啥耗勉肥笼霜陵宠幼驻辩琪刷瑶驶乏巫嫌坛後驱邀咯链逢媒朴瞎桂胎弦衷芝厢抄圾怯腻惫炒娱脂盐荐栽寓伞萝咸疤谐塘禽铅槽杠瑕诶哔怼",
      "N值結果": [
        {
          "最有效率的簡碼個數": 0,
          "字頻加權碼長": 3.5878089098615247
        },
        {
          "最有效率的簡碼個數": 5,
          "字頻加權碼長": 3.3025218908393317
        },
        {
          "最有效率的簡碼個數": 10,
          "字頻加權碼長": 3.210730147679624
        },
        {
          "最有效率的簡碼個數": 25,
          "字頻加權碼長": 3.0734105525517976
        },
        {
          "最有效率的簡碼個數": 50,
          "字頻加權碼長": 2.9629881690474136
        },
        {
          "最有效率的簡碼個數": 75,
          "字頻加權碼長": 2.901349024076712
        },
        {
          "最有效率的簡碼個數": 100,
          "字頻加權碼長": 2.8639238735602457
        },
        {
          "最有效率的簡碼個數": 150,
          "字頻加權碼長": 2.8211460086908944
        },
        {
          "最有效率的簡碼個數": 200,
          "字頻加權碼長": 2.792721008679268
        },
        {
          "最有效率的簡碼個數": 250,
          "字頻加權碼長": 2.773571721881764
        },
        {
          "最有效率的簡碼個數": 300,
          "字頻加權碼長": 2.7604494257257874
        },
        {
          "最有效率的簡碼個數": 400,
          "字頻加權碼長": 2.7461037218605036
        },
        {
          "最有效率的簡碼個數": 500,
          "字頻加權碼長": 2.7413945668286623
        },
        {
          "最有效率的簡碼個數": 600,
          "字頻加權碼長": 2.741388742834807
        },
        {
          "最有效率的簡碼個數": 700,
          "字頻加權碼長": 2.741388742834807
        },
        {
          "最有效率的簡碼個數": 800,
          "字頻加權碼長": 2.741388742834807
        },
        {
          "最有效率的簡碼個數": 900,
          "字頻加權碼長": 2.741388742834807
        },
        {
          "最有效率的簡碼個數": 1000,
          "字頻加權碼長": 2.741388742834807
        },
        {
          "最有效率的簡碼個數": 1100,
          "字頻加權碼長": 2.741388742834807
        },
        {
          "最有效率的簡碼個數": 1200,
          "字頻加權碼長": 2.741388742834807
        },
        {
          "最有效率的簡碼個數": 1300,
          "字頻加權碼長": 2.741388742834807
        },
        {
          "最有效率的簡碼個數": 1400,
          "字頻加權碼長": 2.741388742834807
        },
        {
          "最有效率的簡碼個數": 1500,
          "字頻加權碼長": 2.741388742834807
        },
        {
          "最有效率的簡碼個數": 1600,
          "字頻加權碼長": 2.741388742834807
        },
        {
          "最有效率的簡碼個數": 1700,
          "字頻加權碼長": 2.741388742834807
        },
        {
          "最有效率的簡碼個數": 1800,
          "字頻加權碼長": 2.741388742834807
        },
        {
          "最有效率的簡碼個數": 1900,
          "字頻加權碼長": 2.741388742834807
        },
        {
          "最有效率的簡碼個數": 2000,
          "字頻加權碼長": 2.741388742834807
        }
      ]
    },
    "臺標繁體字頻下之簡碼效率": {
      "完整字符字符串": "的不我是有了在他地以家到得能好生就多中你而之可所自理成都想然要和那行去最作感度後事看也面起高些因分道外法前民意情做美再重物知相性政活加影身四部常其世北校海表吃色她期保品但平空路爸很母孩第原把病星提片比界通球接打先望位建解流量清式直院快住系喜完服近字指程求始制更深房等考功英客持格河吧步男照易基算城切除乎左案黑存低希似增找五局效衣班值亮查雄族跟李配舞玩策被息微修答屋模怕待害慢拿操岸款店群彩察追忙幼威缺婚降幕呼睡派菜拍置朝啊警略右露避藏宜疑困律遇婆麻娘尤武途哈佳桃索述哪概呀暴珍域互楚封懂媒授峰宗震惜爬均后席叔乏肥鞋松零遭姑既貌喊拔琴符荒梅董圾某胎幽刷娃曼桂腰邀腹埋吵盟炸琳崇耗脂赫炒寓逢勉准陵晴蛇嫁嫌弦瞬抄霜芝屁栽衷槽御划嗯怯瞎咯禽袁巫瑕塘郁喂琪荐疤咸婷据愿筑朴啥",
      "N值結果": [
        {
          "最有效率的簡碼個數": 0,
          "字頻加權碼長": 3.722055104360238
        },
        {
          "最有效率的簡碼個數": 5,
          "字頻加權碼長": 3.573956124978162
        },
        {
          "最有效率的簡碼個數": 10,
          "字頻加權碼長": 3.527285978965099
        },
        {
          "最有效率的簡碼個數": 25,
          "字頻加權碼長": 3.4533557688787107
        },
        {
          "最有效率的簡碼個數": 50,
          "字頻加權碼長": 3.387199880322273
        },
        {
          "最有效率的簡碼個數": 75,
          "字頻加權碼長": 3.346144356519587
        },
        {
          "最有效率的簡碼個數": 100,
          "字頻加權碼長": 3.317626907177118
        },
        {
          "最有效率的簡碼個數": 150,
          "字頻加權碼長": 3.2813058812979747
        },
        {
          "最有效率的簡碼個數": 200,
          "字頻加權碼長": 3.262584763066853
        },
        {
          "最有效率的簡碼個數": 250,
          "字頻加權碼長": 3.2523460997339697
        },
        {
          "最有效率的簡碼個數": 300,
          "字頻加權碼長": 3.247808305579396
        },
        {
          "最有效率的簡碼個數": 400,
          "字頻加權碼長": 3.247239379001495
        },
        {
          "最有效率的簡碼個數": 500,
          "字頻加權碼長": 3.247239379001495
        },
        {
          "最有效率的簡碼個數": 600,
          "字頻加權碼長": 3.247239379001495
        },
        {
          "最有效率的簡碼個數": 700,
          "字頻加權碼長": 3.247239379001495
        },
        {
          "最有效率的簡碼個數": 800,
          "字頻加權碼長": 3.247239379001495
        },
        {
          "最有效率的簡碼個數": 900,
          "字頻加權碼長": 3.247239379001495
        },
        {
          "最有效率的簡碼個數": 1000,
          "字頻加權碼長": 3.247239379001495
        },
        {
          "最有效率的簡碼個數": 1100,
          "字頻加權碼長": 3.247239379001495
        },
        {
          "最有效率的簡碼個數": 1200,
          "字頻加權碼長": 3.247239379001495
        },
        {
          "最有效率的簡碼個數": 1300,
          "字頻加權碼長": 3.247239379001495
        },
        {
          "最有效率的簡碼個數": 1400,
          "字頻加權碼長": 3.247239379001495
        },
        {
          "最有效率的簡碼個數": 1500,
          "字頻加權碼長": 3.247239379001495
        },
        {
          "最有效率的簡碼個數": 1600,
          "字頻加權碼長": 3.247239379001495
        },
        {
          "最有效率的簡碼個數": 1700,
          "字頻加權碼長": 3.247239379001495
        },
        {
          "最有效率的簡碼個數": 1800,
          "字頻加權碼長": 3.247239379001495
        },
        {
          "最有效率的簡碼個數": 1900,
          "字頻加權碼長": 3.247239379001495
        },
        {
          "最有效率的簡碼個數": 2000,
          "字頻加權碼長": 3.247239379001495
        }
      ]
    },
    "古籍繁體字頻下之簡碼效率": {
      "完整字符字符串": "之不以而有所也其四是在得中五事能自都行地家後左我相后多可武平作城世道度北和等生高第成校常陵封先前然朝知民字建分始宜因功好位河理外法去通宗重右乎起服就星加海既楚意政置降流母求制除威身表物解更易望原部御清深直李咸追到衣持病近略害疑感情被微比空色策考客美亮叔路修群性再存崇授保案遇震步期待息族律幽袁但喜雄要为暴基他拔增最符男呼房察域述界面董英操避指答接尤舞班幼索品露配效藏数困荒的据珍遭松黑划切式局屋貌禽量似姑均席盟零系时腹桂程希乏肥国过巫逢领惜格算经照想勉赫岸值霜准嫌款蛇婚弦缺了提住琴互书芝嫁完警玩某军郁进会麻活宫曼慢桃来球幕寓埋黄影模从抄琳瑕谓快菜那对佳说别虚途塘发耗怯学衷还实邀众问骑筑应梅动华婆却质腰概临彩岁远低语胜关号把胎许贵难营给机转离种愿强孩看处脂间历怀朴听荐图选废单战钱脚查顺专打随爱务宠责片两龙杠题费没媒标点吃结很员变极资肃杂试睡简峰运满铁读拍课笔派晴颜钟愤话刷刚减桥着调楼构宽驱验盐辩阶区坛槽辈总带择娃锋院汤拥优际栽呀网错测买瞎驻弹谐该遥瞬些忙瑶销店跟镜铅做惨铃灯驶净样拿怼态阵彻晕琪艳娱压萝鞋怕换惫喂找哪",
      "N值結果": [
        {
          "最有效率的簡碼個數": 0,
          "字頻加權碼長": 3.67905503499685
        },
        {
          "最有效率的簡碼個數": 5,
          "字頻加權碼長": 3.5463282054605902
        },
        {
          "最有效率的簡碼個數": 10,
          "字頻加權碼長": 3.508926335419191
        },
        {
          "最有效率的簡碼個數": 25,
          "字頻加權碼長": 3.458857466654388
        },
        {
          "最有效率的簡碼個數": 50,
          "字頻加權碼長": 3.415096584245801
        },
        {
          "最有效率的簡碼個數": 75,
          "字頻加權碼長": 3.3883337494917924
        },
        {
          "最有效率的簡碼個數": 100,
          "字頻加權碼長": 3.3709917057632546
        },
        {
          "最有效率的簡碼個數": 150,
          "字頻加權碼長": 3.352271341738378
        },
        {
          "最有效率的簡碼個數": 200,
          "字頻加權碼長": 3.3434036458318213
        },
        {
          "最有效率的簡碼個數": 250,
          "字頻加權碼長": 3.3396832200319286
        },
        {
          "最有效率的簡碼個數": 300,
          "字頻加權碼長": 3.338323742739642
        },
        {
          "最有效率的簡碼個數": 400,
          "字頻加權碼長": 3.3376392505924777
        },
        {
          "最有效率的簡碼個數": 500,
          "字頻加權碼長": 3.337595071582975
        },
        {
          "最有效率的簡碼個數": 600,
          "字頻加權碼長": 3.337595071582975
        },
        {
          "最有效率的簡碼個數": 700,
          "字頻加權碼長": 3.337595071582975
        },
        {
          "最有效率的簡碼個數": 800,
          "字頻加權碼長": 3.337595071582975
        },
        {
          "最有效率的簡碼個數": 900,
          "字頻加權碼長": 3.337595071582975
        },
        {
          "最有效率的簡碼個數": 1000,
          "字頻加權碼長": 3.337595071582975
        },
        {
          "最有效率的簡碼個數": 1100,
          "字頻加權碼長": 3.337595071582975
        },
        {
          "最有效率的簡碼個數": 1200,
          "字頻加權碼長": 3.337595071582975
        },
        {
          "最有效率的簡碼個數": 1300,
          "字頻加權碼長": 3.337595071582975
        },
        {
          "最有效率的簡碼個數": 1400,
          "字頻加權碼長": 3.337595071582975
        },
        {
          "最有效率的簡碼個數": 1500,
          "字頻加權碼長": 3.337595071582975
        },
        {
          "最有效率的簡碼個數": 1600,
          "字頻加權碼長": 3.337595071582975
        },
        {
          "最有效率的簡碼個數": 1700,
          "字頻加權碼長": 3.337595071582975
        },
        {
          "最有效率的簡碼個數": 1800,
          "字頻加權碼長": 3.337595071582975
        },
        {
          "最有效率的簡碼個數": 1900,
          "字頻加權碼長": 3.337595071582975
        },
        {
          "最有效率的簡碼個數": 2000,
          "字頻加權碼長": 3.337595071582975
        }
      ]
    },
    "繁簡聯合字頻下之簡碼效率": {
      "完整字符字符串": "的不我了是在有这他来你说到就着地时好得以会家后都和对想能之道而那生也多中看要她没些然为过自去可所还理成动国给起进再实最学第感行身作吧度样後事面做知高很点前因发经分情外把法话意民但美两重四从物间相性被政问吃打活加影部常其世北校种海表听却啊色军期保品平空住路爸母孩等别原病星提战片直比界通球脸快接应先望难位更建解流关机量处清完式院刚跟爱龙带找李变系喜强男服该近字指程求始远制许黑转总算城深房满考离功英似五乎客持结格河怕步书微左照易钱基随武哪数题衣拿切除案忙存员低哈希息增阵语错极局慢效领准班华质答众值亮查够雄族害单脚舞配脑楚玩策朝团黄修呀待楼呼屋模运睡怀露娘操岸愿务款店群彩疑察调派追幼威缺铁资号婚简选降幕历试菜区拍右置态买图岁警顺略既松费钟藏避宜宫压困胜律遇据骑贵换婆层喊麻划尤姑责营专途弹佳桃标际索述某封震虚概梅临宗暴珍域互读叔懂媒网赛授峰拥灯验惜辈爬均优杂笔席乏择课肥鞋疯腰零镜幽遭颜谓锋瞬貌惨拔惯琴符荒愤阶董测遥净炸圾颗嗯骗宽胎刷娃彻曼御蛇晕屁盟郁琳构销桂废喂艳晴邀埋腹桥减吵肃铺汤婷赫崇耗脂龄炒钢寓逢嫁键袁筑勉铃啥陵笼霜宠驻辩琪瑶驶嫌巫弦坛驱咯抄链朴瞎芝衷厢栽槽怯腻惫娱盐荐伞萝咸禽疤瑕谐塘铅杠诶哔怼",
      "N值結果": [
        {
          "最有效率的簡碼個數": 0,
          "字頻加權碼長": 3.6944420927492065
        },
        {
          "最有效率的簡碼個數": 5,
          "字頻加權碼長": 3.5007738283403786
        },
        {
          "最有效率的簡碼個數": 10,
          "字頻加權碼長": 3.438460626548971
        },
        {
          "最有效率的簡碼個數": 25,
          "字頻加權碼長": 3.3444748851561417
        },
        {
          "最有效率的簡碼個數": 50,
          "字頻加權碼長": 3.266500291035091
        },
        {
          "最有效率的簡碼個數": 75,
          "字頻加權碼長": 3.221006724653134
        },
        {
          "最有效率的簡碼個數": 100,
          "字頻加權碼長": 3.189533927131588
        },
        {
          "最有效率的簡碼個數": 150,
          "字頻加權碼長": 3.1495436568532256
        },
        {
          "最有效率的簡碼個數": 200,
          "字頻加權碼長": 3.124133007134649
        },
        {
          "最有效率的簡碼個數": 250,
          "字頻加權碼長": 3.1073328159611795
        },
        {
          "最有效率的簡碼個數": 300,
          "字頻加權碼長": 3.09622449286113
        },
        {
          "最有效率的簡碼個數": 400,
          "字頻加權碼長": 3.0836978174782113
        },
        {
          "最有效率的簡碼個數": 500,
          "字頻加權碼長": 3.0796815230532046
        },
        {
          "最有效率的簡碼個數": 600,
          "字頻加權碼長": 3.07967756941106
        },
        {
          "最有效率的簡碼個數": 700,
          "字頻加權碼長": 3.07967756941106
        },
        {
          "最有效率的簡碼個數": 800,
          "字頻加權碼長": 3.07967756941106
        },
        {
          "最有效率的簡碼個數": 900,
          "字頻加權碼長": 3.07967756941106
        },
        {
          "最有效率的簡碼個數": 1000,
          "字頻加權碼長": 3.07967756941106
        },
        {
          "最有效率的簡碼個數": 1100,
          "字頻加權碼長": 3.07967756941106
        },
        {
          "最有效率的簡碼個數": 1200,
          "字頻加權碼長": 3.07967756941106
        },
        {
          "最有效率的簡碼個數": 1300,
          "字頻加權碼長": 3.07967756941106
        },
        {
          "最有效率的簡碼個數": 1400,
          "字頻加權碼長": 3.07967756941106
        },
        {
          "最有效率的簡碼個數": 1500,
          "字頻加權碼長": 3.07967756941106
        },
        {
          "最有效率的簡碼個數": 1600,
          "字頻加權碼長": 3.07967756941106
        },
        {
          "最有效率的簡碼個數": 1700,
          "字頻加權碼長": 3.07967756941106
        },
        {
          "最有效率的簡碼個數": 1800,
          "字頻加權碼長": 3.07967756941106
        },
        {
          "最有效率的簡碼個數": 1900,
          "字頻加權碼長": 3.07967756941106
        },
        {
          "最有效率的簡碼個數": 2000,
          "字頻加權碼長": 3.07967756941106
        }
      ]
    },
    "計算時間": 1770334883979
  },
  "測評結果": {
    "靜態重碼分析": {
      "GB2312": {
        "全碼重碼組數": 242,
        "簡碼重碼組數": 198,
        "全碼重碼字數": 489,
        "簡碼重碼字數": 401,
        "實際字符數": 6764,
        "理論字符數": 6764,
        "字集覆蓋率": 1
      },
      "通用規範": {
        "全碼重碼組數": 375,
        "簡碼重碼組數": 314,
        "全碼重碼字數": 766,
        "簡碼重碼字數": 642,
        "實際字符數": 8105,
        "理論字符數": 8105,
        "字集覆蓋率": 1
      },
      "常用國字": {
        "全碼重碼組數": 123,
        "簡碼重碼組數": 100,
        "全碼重碼字數": 247,
        "簡碼重碼字數": 201,
        "實際字符數": 4808,
        "理論字符數": 4808,
        "字集覆蓋率": 1
      },
      "CJK基本": {
        "全碼重碼組數": 2687,
        "簡碼重碼組數": 2526,
        "全碼重碼字數": 5937,
        "簡碼重碼字數": 5581,
        "實際字符數": 20992,
        "理論字符數": 20992,
        "字集覆蓋率": 1
      },
      "到CJK擴A": {
        "全碼重碼組數": 4184,
        "簡碼重碼組數": 3993,
        "全碼重碼字數": 9655,
        "簡碼重碼字數": 9222,
        "實際字符數": 27584,
        "理論字符數": 27584,
        "字集覆蓋率": 1
      },
      "到CJK擴B": {
        "全碼重碼組數": 14346,
        "簡碼重碼組數": 14115,
        "全碼重碼字數": 39755,
        "簡碼重碼字數": 39101,
        "實際字符數": 70304,
        "理論字符數": 70304,
        "字集覆蓋率": 1
      },
      "到CJK擴C": {
        "全碼重碼組數": 15402,
        "簡碼重碼組數": 15169,
        "全碼重碼字數": 42949,
        "簡碼重碼字數": 42277,
        "實際字符數": 74458,
        "理論字符數": 74464,
        "字集覆蓋率": 0.9999194241512678
      },
      "到CJK擴D": {
        "全碼重碼組數": 15460,
        "簡碼重碼組數": 15228,
        "全碼重碼字數": 43121,
        "簡碼重碼字數": 42450,
        "實際字符數": 74680,
        "理論字符數": 74686,
        "字集覆蓋率": 0.999919663658517
      },
      "到CJK擴E": {
        "全碼重碼組數": 16865,
        "簡碼重碼組數": 16632,
        "全碼重碼字數": 47566,
        "簡碼重碼字數": 46873,
        "實際字符數": 80442,
        "理論字符數": 80460,
        "字集覆蓋率": 0.9997762863534676
      },
      "到CJK擴F": {
        "全碼重碼組數": 18743,
        "簡碼重碼組數": 18499,
        "全碼重碼字數": 53645,
        "簡碼重碼字數": 52911,
        "實際字符數": 87915,
        "理論字符數": 87933,
        "字集覆蓋率": 0.9997952986933233
      },
      "到CJK擴G": {
        "全碼重碼組數": 19973,
        "簡碼重碼組數": 19733,
        "全碼重碼字數": 57736,
        "簡碼重碼字數": 56990,
        "實際字符數": 92854,
        "理論字符數": 92872,
        "字集覆蓋率": 0.9998061848565768
      },
      "到CJK擴H": {
        "全碼重碼組數": 20947,
        "簡碼重碼組數": 20708,
        "全碼重碼字數": 61066,
        "簡碼重碼字數": 60310,
        "實際字符數": 97046,
        "理論字符數": 97064,
        "字集覆蓋率": 0.999814555344927
      },
      "到CJK擴I": {
        "全碼重碼組數": 21121,
        "簡碼重碼組數": 20884,
        "全碼重碼字數": 61564,
        "簡碼重碼字數": 60809,
        "實際字符數": 97668,
        "理論字符數": 97686,
        "字集覆蓋率": 0.9998157361341441
      },
      "到CJK擴J": {
        "全碼重碼組數": 21121,
        "簡碼重碼組數": 20884,
        "全碼重碼字數": 61564,
        "簡碼重碼字數": 60809,
        "實際字符數": 97668,
        "理論字符數": 101984,
        "字集覆蓋率": 0.9576796360213367
      },
      "更新時間": "2026-02-08T21:21:08.715Z"
    },
    "動態選重分析": {
      "知乎簡體動態選重率": {
        "全碼": 0.0003545380432536447,
        "簡碼": 0.00022543202750270957
      },
      "北語簡體動態選重率": {
        "全碼": 0.000699294262244554,
        "簡碼": 0.00045671451816618194
      },
      "臺標繁體動態選重率": {
        "全碼": 0.0016578450497638417,
        "簡碼": 0.0009744275320002231
      },
      "古籍繁體動態選重率": {
        "全碼": 0.005405206162119061,
        "簡碼": 0.0036435407833610473
      },
      "繁簡聯合動態選重率": {
        "全碼": 0.002352745408579394,
        "簡碼": 0.0014826386648727895
      },
      "知乎簡體動態選重率原序": {
        "全碼": 0.00036848904495566755,
        "簡碼": 0.00036848904495566755
      },
      "北語簡體動態選重率原序": {
        "全碼": 0.0007654511924489952,
        "簡碼": 0.0007654511924489952
      },
      "臺標繁體動態選重率原序": {
        "全碼": 0.02579233556585121,
        "簡碼": 0.02579233556585121
      },
      "古籍繁體動態選重率原序": {
        "全碼": 0.02453523727507442,
        "簡碼": 0.02453523727507442
      },
      "繁簡聯合動態選重率原序": {
        "全碼": 0.017776085329442713,
        "簡碼": 0.017776085329442713
      },
      "更新時間": "2026-02-08T21:21:05.285Z"
    },
    "候選個數分析": {
      "GB2312": {
        "最大候選個數": 3,
        "編碼列表": [
          "vkwf",
          "vksr",
          "vkdj",
          "hnyk",
          "vkdm"
        ]
      },
      "通用規範": {
        "最大候選個數": 4,
        "編碼列表": [
          "gvi"
        ]
      },
      "常用國字": {
        "最大候選個數": 3,
        "編碼列表": [
          "kzkg"
        ]
      },
      "CJK基本": {
        "最大候選個數": 6,
        "編碼列表": [
          "dknk",
          "fycn",
          "jnqo",
          "lgcq"
        ]
      },
      "到CJK擴A": {
        "最大候選個數": 9,
        "編碼列表": [
          "mrrj"
        ]
      },
      "到CJK擴B": {
        "最大候選個數": 25,
        "編碼列表": [
          "krrq"
        ]
      },
      "到CJK擴C": {
        "最大候選個數": 25,
        "編碼列表": [
          "krrq"
        ]
      },
      "到CJK擴D": {
        "最大候選個數": 25,
        "編碼列表": [
          "krrq"
        ]
      },
      "到CJK擴E": {
        "最大候選個數": 26,
        "編碼列表": [
          "krrq"
        ]
      },
      "到CJK擴F": {
        "最大候選個數": 26,
        "編碼列表": [
          "krrq"
        ]
      },
      "到CJK擴G": {
        "最大候選個數": 28,
        "編碼列表": [
          "krrq"
        ]
      },
      "到CJK擴H": {
        "最大候選個數": 28,
        "編碼列表": [
          "krrq"
        ]
      },
      "到CJK擴I": {
        "最大候選個數": 28,
        "編碼列表": [
          "krrq"
        ]
      },
      "到CJK擴J": {
        "最大候選個數": 28,
        "編碼列表": [
          "krrq"
        ]
      },
      "字符數": 97668,
      "更新時間": "2026-02-08T21:21:09.381Z"
    },
    "速度當量分析": {
      "知乎簡體字頻全碼速度當量": 1.3215987294446685,
      "北語簡體字頻全碼速度當量": 1.3192660289812406,
      "臺標繁體字頻全碼速度當量": 1.336412862868928,
      "古籍繁體字頻全碼速度當量": 1.3370385109147687,
      "繁簡聯合字頻全碼速度當量": 1.3297787423676508,
      "知乎簡體字頻一級簡碼速度當量": 1.3203452625573855,
      "北語簡體字頻一級簡碼速度當量": 1.3210581477718937,
      "臺標繁體字頻一級簡碼速度當量": 1.3370775246361155,
      "古籍繁體字頻一級簡碼速度當量": 1.3431308149203771,
      "繁簡聯合字頻一級簡碼速度當量": 1.33163531262604,
      "知乎簡體字頻二級簡碼速度當量": 1.3159424422632533,
      "北語簡體字頻二級簡碼速度當量": 1.3176037400568987,
      "臺標繁體字頻二級簡碼速度當量": 1.335227857219276,
      "古籍繁體字頻二級簡碼速度當量": 1.3412045754790007,
      "繁簡聯合字頻二級簡碼速度當量": 1.3296476470129377,
      "知乎簡體字頻全部簡碼速度當量": 1.3093381695580188,
      "北語簡體字頻全部簡碼速度當量": 1.3144359458651027,
      "臺標繁體字頻全部簡碼速度當量": 1.334728317131217,
      "古籍繁體字頻全部簡碼速度當量": 1.3396883892107527,
      "繁簡聯合字頻全部簡碼速度當量": 1.3298141694470387,
      "更新時間": "2026-02-08T21:21:10.971Z"
    },
    "簡碼效率分析": {
      "知乎簡體字頻下之簡碼效率": {
        "完整字符字符串": "的不是我在这了就你和有以来为都到说能会他多好学得后那国家问想要而最所实时也之发经自其没前可看成很种地点做些着高还中事对理过感样生意给两然第她动性但用去子天先分比度再面当因进原完作等吃答知题跟道定被网情业起从行别找期专变更关文常法公打相身直机把美部间校重电四外应质男喜数爱基友考接加结话提通算平该水单表区活位买世量系始影品总物选语民程资难带图听清书制路孩简保强玩流建格微读刚界钱左处战哪海拿历试北某英哈字片求色黑服政式深运持近照转指快五空员易望案据够房住标概存满准球军优除离城错远随功许务费却吧脑调值低希极众母院华班客模验乎领似效星换步楼爸拍配怕课际号群病态慢择遇切修压岁脸啊衣团愿懂睡层婚族害互店营待追黄息查啥笔武朝顺赛销律缺荐李谓增局构款测责阶略置既划铁姑怀刷暴龙操菜麻键右减警钟疑娘尤述邀亮颜贵脚索弹杂镜辈察均楚域河松婆派降策藏避惯媒临宗虚威露困拥封零骗胜彩符呼链貌幕舞雄龄忙鞋叔炸槽骑宜灯授阵途净钢肥震屁筑炒废幼惜宽嫌佳抄宫汤腰瞬疯辩琴吵郁乏彻喊脂娱耗颗铺爬屋峰瞎拔梅珍惨遭曼腹胎桥嫁盟嗯宠愤崇娃坛圾荒席驱幽呀锋桃艳喂埋遥岸勉肃盐萝驶腻赫御朴蛇董晕笼芝逢驻弦谐袁咸衷杠铃霜桂陵巫晴伞怼厢寓铅哔琳瑕塘咯琪疤婷栽禽怯瑶惫",
        "N值結果": [
          {
            "最有效率的簡碼個數": 0,
            "字頻加權碼長": 3.503406045415555
          },
          {
            "最有效率的簡碼個數": 5,
            "字頻加權碼長": 3.212098076875981
          },
          {
            "最有效率的簡碼個數": 10,
            "字頻加權碼長": 3.1338617993311537
          },
          {
            "最有效率的簡碼個數": 25,
            "字頻加權碼長": 2.988484220595086
          },
          {
            "最有效率的簡碼個數": 50,
            "字頻加權碼長": 2.8567554565241755
          },
          {
            "最有效率的簡碼個數": 75,
            "字頻加權碼長": 2.768636796773699
          },
          {
            "最有效率的簡碼個數": 100,
            "字頻加權碼長": 2.7141443901256257
          },
          {
            "最有效率的簡碼個數": 150,
            "字頻加權碼長": 2.6482883350911868
          },
          {
            "最有效率的簡碼個數": 200,
            "字頻加權碼長": 2.6127792207590743
          },
          {
            "最有效率的簡碼個數": 250,
            "字頻加權碼長": 2.5883443007780125
          },
          {
            "最有效率的簡碼個數": 300,
            "字頻加權碼長": 2.571254533693061
          },
          {
            "最有效率的簡碼個數": 400,
            "字頻加權碼長": 2.5545373816535717
          },
          {
            "最有效率的簡碼個數": 500,
            "字頻加權碼長": 2.54972672506667
          },
          {
            "最有效率的簡碼個數": 600,
            "字頻加權碼長": 2.5496403330561295
          },
          {
            "最有效率的簡碼個數": 700,
            "字頻加權碼長": 2.5496403330561295
          },
          {
            "最有效率的簡碼個數": 800,
            "字頻加權碼長": 2.5496403330561295
          },
          {
            "最有效率的簡碼個數": 900,
            "字頻加權碼長": 2.5496403330561295
          },
          {
            "最有效率的簡碼個數": 1000,
            "字頻加權碼長": 2.5496403330561295
          },
          {
            "最有效率的簡碼個數": 1100,
            "字頻加權碼長": 2.5496403330561295
          },
          {
            "最有效率的簡碼個數": 1200,
            "字頻加權碼長": 2.5496403330561295
          },
          {
            "最有效率的簡碼個數": 1300,
            "字頻加權碼長": 2.5496403330561295
          },
          {
            "最有效率的簡碼個數": 1400,
            "字頻加權碼長": 2.5496403330561295
          },
          {
            "最有效率的簡碼個數": 1500,
            "字頻加權碼長": 2.5496403330561295
          },
          {
            "最有效率的簡碼個數": 1600,
            "字頻加權碼長": 2.5496403330561295
          },
          {
            "最有效率的簡碼個數": 1700,
            "字頻加權碼長": 2.5496403330561295
          },
          {
            "最有效率的簡碼個數": 1800,
            "字頻加權碼長": 2.5496403330561295
          },
          {
            "最有效率的簡碼個數": 1900,
            "字頻加權碼長": 2.5496403330561295
          },
          {
            "最有效率的簡碼個數": 2000,
            "字頻加權碼長": 2.5496403330561295
          }
        ]
      },
      "北語簡體字頻下之簡碼效率": {
        "完整字符字符串": "的不我了是在这他来你说到就着那和有地她为好得会后以都想能之道而样也事多家子时看点要前发经中没些然意过自去可所成天还两对动国给起问进再种实最学高第感生其身吧面做知等很情理把话但当先完四从用跟间被找原吃打变法行定性分听作却啊因军外度住公相别色部战直重脸比快水应难更美位关机接文处望常清刚爱龙空带李平强男该路海加远活解电世表许期黑转总算城孩校始满物离似通五乎量结怕流指书微步左喜影深钱提随服武哪数房题衣拿星功系业近界字民切忙员哈制友息保片阵语错极慢领准华质答众够求害单脚脑楚专北格朝族团母亮客照易黄修球呀院玩待楼呼英低持政运睡希网怀露娘式除考建愿程务品疑调爸派铁资群号病威追简基选历试存区右态买局班图岁顺既松费拍钟警宫压河查察胜遇据骑贵屋换层喊婚划置模舞姑麻责营案嗯店弹标际某封藏震虚梅临宗索婆值读叔雄赛略拥灯菜验暴辈懂效优杂彩笔惜避配择课峰疯腰镜幽降颜谓操锋瞬尤概增困律惨惯互策席缺愤阶测遥幕净珍爬炸颗佳骗拔宽遭彻御貌述琴蛇晕屁零盟途郁琳构销废曼宜喂艳晴董埋款荒域授桥减岸肃铺汤婷赫符吵鞋均龄钢嫁键袁筑崇娃桃铃腹啥耗勉肥笼霜陵宠幼驻辩琪刷瑶驶乏巫嫌坛後驱邀咯链逢媒朴瞎桂胎弦衷芝厢抄圾怯腻惫炒娱脂盐荐栽寓伞萝咸疤谐塘禽铅槽杠瑕诶哔怼",
        "N值結果": [
          {
            "最有效率的簡碼個數": 0,
            "字頻加權碼長": 3.4980880275170483
          },
          {
            "最有效率的簡碼個數": 5,
            "字頻加權碼長": 3.2128010084948566
          },
          {
            "最有效率的簡碼個數": 10,
            "字頻加權碼長": 3.114716431974086
          },
          {
            "最有效率的簡碼個數": 25,
            "字頻加權碼長": 2.975087769282327
          },
          {
            "最有效率的簡碼個數": 50,
            "字頻加權碼長": 2.8568881439829323
          },
          {
            "最有效率的簡碼個數": 75,
            "字頻加權碼長": 2.7787095664613317
          },
          {
            "最有效率的簡碼個數": 100,
            "字頻加權碼長": 2.7312026005811805
          },
          {
            "最有效率的簡碼個數": 150,
            "字頻加權碼長": 2.6803982671797506
          },
          {
            "最有效率的簡碼個數": 200,
            "字頻加權碼長": 2.649833850425211
          },
          {
            "最有效率的簡碼個數": 250,
            "字頻加權碼長": 2.6289324234762157
          },
          {
            "最有效率的簡碼個數": 300,
            "字頻加權碼長": 2.614389297819214
          },
          {
            "最有效率的簡碼個數": 400,
            "字頻加權碼長": 2.598341237749917
          },
          {
            "最有效率的簡碼個數": 500,
            "字頻加權碼長": 2.5927913446050552
          },
          {
            "最有效率的簡碼個數": 600,
            "字頻加權碼長": 2.592650944753177
          },
          {
            "最有效率的簡碼個數": 700,
            "字頻加權碼長": 2.592650944753177
          },
          {
            "最有效率的簡碼個數": 800,
            "字頻加權碼長": 2.592650944753177
          },
          {
            "最有效率的簡碼個數": 900,
            "字頻加權碼長": 2.592650944753177
          },
          {
            "最有效率的簡碼個數": 1000,
            "字頻加權碼長": 2.592650944753177
          },
          {
            "最有效率的簡碼個數": 1100,
            "字頻加權碼長": 2.592650944753177
          },
          {
            "最有效率的簡碼個數": 1200,
            "字頻加權碼長": 2.592650944753177
          },
          {
            "最有效率的簡碼個數": 1300,
            "字頻加權碼長": 2.592650944753177
          },
          {
            "最有效率的簡碼個數": 1400,
            "字頻加權碼長": 2.592650944753177
          },
          {
            "最有效率的簡碼個數": 1500,
            "字頻加權碼長": 2.592650944753177
          },
          {
            "最有效率的簡碼個數": 1600,
            "字頻加權碼長": 2.592650944753177
          },
          {
            "最有效率的簡碼個數": 1700,
            "字頻加權碼長": 2.592650944753177
          },
          {
            "最有效率的簡碼個數": 1800,
            "字頻加權碼長": 2.592650944753177
          },
          {
            "最有效率的簡碼個數": 1900,
            "字頻加權碼長": 2.592650944753177
          },
          {
            "最有效率的簡碼個數": 2000,
            "字頻加權碼長": 2.592650944753177
          }
        ]
      },
      "臺標繁體字頻下之簡碼效率": {
        "完整字符字符串": "的不我是在了他地以有成家到得能那好生就多事子和中高你而前之意可所自理都天想性然要其行去最作感度後她公看期也面起用些因原分道外法水民先文情做定美再重物知相政活加影身四完部常世北校海表吃等色保友品但平空路爸很母孩第把病星提片比界通球接打望位建找解流量清式直院快跟住系喜服近字指程求始制更深房考功英客持格河吧步男照易基算城切除乎左案黑存低希似增五局效衣班值亮查雄族李配舞玩策被息微修答屋模怕待害慢拿操岸款店群彩察追忙幼威缺婚降幕呼睡派菜拍置朝啊警略右露避藏宜疑困律遇婆麻娘尤武途哈佳桃索述哪概呀暴珍域互楚封懂媒授峰宗震惜爬均后席叔乏肥鞋松零遭姑既貌喊拔琴符荒梅董圾某胎幽刷娃曼桂腰邀腹埋吵盟炸琳崇耗脂赫炒寓逢勉准陵晴蛇嫁嫌嗯弦瞬抄霜芝屁栽衷槽御划怯瞎咯禽袁巫瑕塘郁喂琪荐疤咸婷据愿筑朴啥",
        "N值結果": [
          {
            "最有效率的簡碼個數": 0,
            "字頻加權碼長": 3.6598711154848154
          },
          {
            "最有效率的簡碼個數": 5,
            "字頻加權碼長": 3.511130579025477
          },
          {
            "最有效率的簡碼個數": 10,
            "字頻加權碼長": 3.4673000237284084
          },
          {
            "最有效率的簡碼個數": 25,
            "字頻加權碼長": 3.385362978110796
          },
          {
            "最有效率的簡碼個數": 50,
            "字頻加權碼長": 3.305843366681927
          },
          {
            "最有效率的簡碼個數": 75,
            "字頻加權碼長": 3.255967458352168
          },
          {
            "最有效率的簡碼個數": 100,
            "字頻加權碼長": 3.222212149764488
          },
          {
            "最有效率的簡碼個數": 150,
            "字頻加權碼長": 3.1804595879753332
          },
          {
            "最有效率的簡碼個數": 200,
            "字頻加權碼長": 3.15942645118303
          },
          {
            "最有效率的簡碼個數": 250,
            "字頻加權碼長": 3.148173502946574
          },
          {
            "最有效率的簡碼個數": 300,
            "字頻加權碼長": 3.1427853445292646
          },
          {
            "最有效率的簡碼個數": 400,
            "字頻加權碼長": 3.1417988025803836
          },
          {
            "最有效率的簡碼個數": 500,
            "字頻加權碼長": 3.1417988025803836
          },
          {
            "最有效率的簡碼個數": 600,
            "字頻加權碼長": 3.1417988025803836
          },
          {
            "最有效率的簡碼個數": 700,
            "字頻加權碼長": 3.1417988025803836
          },
          {
            "最有效率的簡碼個數": 800,
            "字頻加權碼長": 3.1417988025803836
          },
          {
            "最有效率的簡碼個數": 900,
            "字頻加權碼長": 3.1417988025803836
          },
          {
            "最有效率的簡碼個數": 1000,
            "字頻加權碼長": 3.1417988025803836
          },
          {
            "最有效率的簡碼個數": 1100,
            "字頻加權碼長": 3.1417988025803836
          },
          {
            "最有效率的簡碼個數": 1200,
            "字頻加權碼長": 3.1417988025803836
          },
          {
            "最有效率的簡碼個數": 1300,
            "字頻加權碼長": 3.1417988025803836
          },
          {
            "最有效率的簡碼個數": 1400,
            "字頻加權碼長": 3.1417988025803836
          },
          {
            "最有效率的簡碼個數": 1500,
            "字頻加權碼長": 3.1417988025803836
          },
          {
            "最有效率的簡碼個數": 1600,
            "字頻加權碼長": 3.1417988025803836
          },
          {
            "最有效率的簡碼個數": 1700,
            "字頻加權碼長": 3.1417988025803836
          },
          {
            "最有效率的簡碼個數": 1800,
            "字頻加權碼長": 3.1417988025803836
          },
          {
            "最有效率的簡碼個數": 1900,
            "字頻加權碼長": 3.1417988025803836
          },
          {
            "最有效率的簡碼個數": 2000,
            "字頻加權碼長": 3.1417988025803836
          }
        ]
      },
      "古籍繁體字頻下之簡碼效率": {
        "完整字符字符串": "之不以其而所也在四事有子是得中五公天能等自高成都行先地前家後左我相和文后多可武平作城世道度北生第意校常陵封然朝知民字建用分始水宜原因功好位河理外法去通宗重右乎起服定就星加海既楚政置降流母求制除性威身表物解更易望期部御清深直李咸为追到衣持病近略害疑感情被微比空色策考客美亮叔路修群再存崇授保案遇震步待息族律幽袁但喜雄要暴基他拔增最符男呼房察域述界面董英操避友指答接尤舞班幼索品露配效经藏数困荒的据珍遭松黑划切式局屋貌禽量似姑均席盟完零系腹桂程希乏肥国过巫逢领惜格算照想勉赫岸值霜准嫌款蛇婚弦缺了提住琴互书芝嫁那警发时玩某军郁进会麻当活宫曼慢桃问来球幕寓埋黄影模从抄琳瑕谓快菜佳说别虚途塘耗怯学衷种还实邀众骑筑应梅动华婆却质腰概临专彩岁远低对业语胜关号把胎许贵难两营给机转离愿强点孩看处脂间历怀朴听变荐图选废单战钱脚查顺打随爱务宠责片龙杠题费没媒标吃结很员极资肃杂试睡简峰运满铁读拍课笔派晴颜钟愤话刷刚减桥着调楼构宽驱验盐辩阶区坛网槽辈总带择娃锋院汤拥优际栽呀跟错测买瞎驻弹谐该遥瞬些样忙瑶销店镜铅做找惨铃灯驶净拿怼态阵彻晕琪艳娱压萝鞋怕换惫电喂哪",
        "N值結果": [
          {
            "最有效率的簡碼個數": 0,
            "字頻加權碼長": 3.6102242781982414
          },
          {
            "最有效率的簡碼個數": 5,
            "字頻加權碼長": 3.476592020467316
          },
          {
            "最有效率的簡碼個數": 10,
            "字頻加權碼長": 3.438048942180557
          },
          {
            "最有效率的簡碼個數": 25,
            "字頻加權碼長": 3.375979056835535
          },
          {
            "最有效率的簡碼個數": 50,
            "字頻加權碼長": 3.3206973919499805
          },
          {
            "最有效率的簡碼個數": 75,
            "字頻加權碼長": 3.2908475935322756
          },
          {
            "最有效率的簡碼個數": 100,
            "字頻加權碼長": 3.270497294156961
          },
          {
            "最有效率的簡碼個數": 150,
            "字頻加權碼長": 3.2485950904479894
          },
          {
            "最有效率的簡碼個數": 200,
            "字頻加權碼長": 3.23869523931952
          },
          {
            "最有效率的簡碼個數": 250,
            "字頻加權碼長": 3.2342678113676215
          },
          {
            "最有效率的簡碼個數": 300,
            "字頻加權碼長": 3.2325675080020573
          },
          {
            "最有效率的簡碼個數": 400,
            "字頻加權碼長": 3.231721772820225
          },
          {
            "最有效率的簡碼個數": 500,
            "字頻加權碼長": 3.231654582805774
          },
          {
            "最有效率的簡碼個數": 600,
            "字頻加權碼長": 3.231654582805774
          },
          {
            "最有效率的簡碼個數": 700,
            "字頻加權碼長": 3.231654582805774
          },
          {
            "最有效率的簡碼個數": 800,
            "字頻加權碼長": 3.231654582805774
          },
          {
            "最有效率的簡碼個數": 900,
            "字頻加權碼長": 3.231654582805774
          },
          {
            "最有效率的簡碼個數": 1000,
            "字頻加權碼長": 3.231654582805774
          },
          {
            "最有效率的簡碼個數": 1100,
            "字頻加權碼長": 3.231654582805774
          },
          {
            "最有效率的簡碼個數": 1200,
            "字頻加權碼長": 3.231654582805774
          },
          {
            "最有效率的簡碼個數": 1300,
            "字頻加權碼長": 3.231654582805774
          },
          {
            "最有效率的簡碼個數": 1400,
            "字頻加權碼長": 3.231654582805774
          },
          {
            "最有效率的簡碼個數": 1500,
            "字頻加權碼長": 3.231654582805774
          },
          {
            "最有效率的簡碼個數": 1600,
            "字頻加權碼長": 3.231654582805774
          },
          {
            "最有效率的簡碼個數": 1700,
            "字頻加權碼長": 3.231654582805774
          },
          {
            "最有效率的簡碼個數": 1800,
            "字頻加權碼長": 3.231654582805774
          },
          {
            "最有效率的簡碼個數": 1900,
            "字頻加權碼長": 3.231654582805774
          },
          {
            "最有效率的簡碼個數": 2000,
            "字頻加權碼長": 3.231654582805774
          }
        ]
      },
      "繁簡聯合字頻下之簡碼效率": {
        "完整字符字符串": "的不我了是在这他来你说到就着那和有地她为好得以会成家后都想能之道而生样也事多子中高时看点要前发经没些然意过自去可所天还理两对动国性给起问进再其种实最学第感行身作吧度後公期面做知用等很因原分情外把法话水民先文但当定美完重四从物跟间相被政找吃打活变加影部常世北校海表听却啊色军保友品平空住路爸母孩别病星提战片直比界通球脸快接应望难位更建解流关机量处清式院刚爱龙带李系喜强男服该近字指程求始远制电许黑转总算城深房满考离功英似五乎客持结格河怕步书微左照易钱基随武哪数题衣拿切业除案忙存员低哈希息增阵语错极局慢效领准班华质答众值亮查够雄族害单脚舞配脑楚专玩策朝团黄修呀待楼呼屋模运睡网怀露娘操岸愿务款店群彩疑察调派追幼威缺铁资号婚简选降幕历试菜区拍右置态买图岁警顺略既松费钟藏避宜宫压困胜律遇据骑贵换婆层喊麻划尤姑责营嗯途弹佳桃标际索述某封震虚概梅临宗暴珍域互读叔懂媒赛授峰拥灯验惜辈爬均优杂笔席乏择课肥鞋疯腰零镜幽遭颜谓锋瞬貌惨拔惯琴符荒愤阶董测遥净炸圾颗骗宽胎刷娃彻曼御蛇晕屁盟郁琳构销桂废喂艳晴邀埋腹桥减吵肃铺汤婷赫崇耗脂龄炒钢寓逢嫁键袁筑勉铃啥陵笼霜宠驻辩琪瑶驶嫌巫弦坛驱咯抄链朴瞎芝衷厢栽槽怯腻惫娱盐荐伞萝咸禽疤瑕谐塘铅杠诶哔怼",
        "N值結果": [
          {
            "最有效率的簡碼個數": 0,
            "字頻加權碼長": 3.6246621476281216
          },
          {
            "最有效率的簡碼個數": 5,
            "字頻加權碼長": 3.4309938832193
          },
          {
            "最有效率的簡碼個數": 10,
            "字頻加權碼長": 3.364408765658887
          },
          {
            "最有效率的簡碼個數": 25,
            "字頻加權碼長": 3.269093762680771
          },
          {
            "最有效率的簡碼個數": 50,
            "字頻加權碼長": 3.1834677311144333
          },
          {
            "最有效率的簡碼個數": 75,
            "字頻加權碼長": 3.1275399549508998
          },
          {
            "最有效率的簡碼個數": 100,
            "字頻加權碼長": 3.0888024349323175
          },
          {
            "最有效率的簡碼個數": 150,
            "字頻加權碼長": 3.0403957612834223
          },
          {
            "最有效率的簡碼個數": 200,
            "字頻加權碼長": 3.01251156429756
          },
          {
            "最有效率的簡碼個數": 250,
            "字頻加權碼長": 2.9941400524189863
          },
          {
            "最有效率的簡碼個數": 300,
            "字頻加權碼長": 2.981820955081998
          },
          {
            "最有效率的簡碼個數": 400,
            "字頻加權碼長": 2.967989997498019
          },
          {
            "最有效率的簡碼個數": 500,
            "字頻加權碼長": 2.9631546130565862
          },
          {
            "最有效率的簡碼個數": 600,
            "字頻加權碼長": 2.9630411038001356
          },
          {
            "最有效率的簡碼個數": 700,
            "字頻加權碼長": 2.9630411038001356
          },
          {
            "最有效率的簡碼個數": 800,
            "字頻加權碼長": 2.9630411038001356
          },
          {
            "最有效率的簡碼個數": 900,
            "字頻加權碼長": 2.9630411038001356
          },
          {
            "最有效率的簡碼個數": 1000,
            "字頻加權碼長": 2.9630411038001356
          },
          {
            "最有效率的簡碼個數": 1100,
            "字頻加權碼長": 2.9630411038001356
          },
          {
            "最有效率的簡碼個數": 1200,
            "字頻加權碼長": 2.9630411038001356
          },
          {
            "最有效率的簡碼個數": 1300,
            "字頻加權碼長": 2.9630411038001356
          },
          {
            "最有效率的簡碼個數": 1400,
            "字頻加權碼長": 2.9630411038001356
          },
          {
            "最有效率的簡碼個數": 1500,
            "字頻加權碼長": 2.9630411038001356
          },
          {
            "最有效率的簡碼個數": 1600,
            "字頻加權碼長": 2.9630411038001356
          },
          {
            "最有效率的簡碼個數": 1700,
            "字頻加權碼長": 2.9630411038001356
          },
          {
            "最有效率的簡碼個數": 1800,
            "字頻加權碼長": 2.9630411038001356
          },
          {
            "最有效率的簡碼個數": 1900,
            "字頻加權碼長": 2.9630411038001356
          },
          {
            "最有效率的簡碼個數": 2000,
            "字頻加權碼長": 2.9630411038001356
          }
        ]
      },
      "計算時間": 1770585672912
    }
  }
}